README.md
pkcrypt2.py
setup.py
x85.py
pkcrypt2.egg-info/PKG-INFO
pkcrypt2.egg-info/SOURCES.txt
pkcrypt2.egg-info/dependency_links.txt
pkcrypt2.egg-info/requires.txt
pkcrypt2.egg-info/top_level.txt